{
  "generator-jhipster": {
    "applicationType": "monolith",
    "authenticationType": "oauth2",
    "baseName": "ISO",
    "buildTool": "maven",
    "cacheProvider": "no",
    "clientFramework": "angular",
    "clientTestFrameworks": [],
    "clientTheme": "none",
    "creationTimestamp": 1737687432022,
    "databaseType": "sql",
    "devDatabaseType": "mariadb",
    "devServerPort": 4200,
    "enableGradleEnterprise": null,
    "enableHibernateCache": false,
    "enableSwaggerCodegen": false,
    "enableTranslation": true,
    "entities": [
      "Convert",
      "Evaluator",
      "Frequency",
      "Title",
      "Parts",
      "CheckTarget",
      "CheckerGroup",
      "CheckLevel",
      "Criteria",
      "CriteriaGroup",
      "ReportType",
      "SampleReport",
      "InspectionReportTitles",
      "SampleReportCriteria",
      "Plan",
      "Report",
      "ReportCriteria",
      "ReportTitle",
      "Script",
      "Source",
      "Fields"
    ],
    "feignClient": null,
    "gradleEnterpriseHost": null,
    "jhipsterVersion": "8.2.1",
    "languages": ["vi"],
    "lastLiquibaseTimestamp": 1740476746000,
    "messageBroker": false,
    "microfrontend": null,
    "microfrontends": [],
    "nativeLanguage": "vi",
    "packageName": "com.mycompany.myapp",
    "prodDatabaseType": "mariadb",
    "reactive": false,
    "searchEngine": false,
    "serverPort": null,
    "serverSideOptions": [],
    "serviceDiscoveryType": false,
    "skipUserManagement": true,
    "syncUserWithIdp": null,
    "testFrameworks": [],
    "websocket": false,
    "withAdminUi": true
  }
}
